circuitanimlib/__init__.py
circuitanimlib/circuit.py
circuitanimlib/logic.py
manimlib/__init__.py
manimlib/config.py
manimlib/constants.py
manimlib/extract_scene.py
manimlib/imports.py
circuitanimlib-1.0.0.dist-info/LICENSE
circuitanimlib-1.0.0.dist-info/METADATA
circuitanimlib-1.0.0.dist-info/WHEEL
circuitanimlib-1.0.0.dist-info/top_level.txt
circuitanimlib-1.0.0.dist-info/RECORD
